openpdi/__init__.py
openpdi/__version__.py
openpdi/converters.py
openpdi/data.py
openpdi/validators.py
openpdi/meta/ois/schema.json
openpdi/meta/ois/WAPO/meta.json
openpdi/meta/uof/schema.json
openpdi/meta/uof/CA/meta.json
openpdi/meta/uof/CT/meta.json
openpdi/meta/uof/DE/meta.json
openpdi/meta/uof/IN/meta.json
openpdi/meta/uof/LA/meta.json
openpdi/meta/uof/MA/meta.json
openpdi/meta/uof/MD/meta.json
openpdi/meta/uof/NM/meta.json
openpdi/meta/uof/NV/meta.json
openpdi/meta/uof/OH/meta.json
openpdi/meta/uof/OK/meta.json
openpdi/meta/uof/PA/meta.json
openpdi/meta/uof/TX/meta.json
openpdi/meta/uof/WI/meta.json
openpdi-0.2.4.dist-info/LICENSE
openpdi-0.2.4.dist-info/METADATA
openpdi-0.2.4.dist-info/WHEEL
openpdi-0.2.4.dist-info/top_level.txt
openpdi-0.2.4.dist-info/RECORD
