Metadata-Version: 2.1
Name: openpdi
Version: 0.2.4
Summary: A library for working with data submitted to the PDI.
Home-page: https://github.com/OpenPDI/openpdi
Author: Joseph Kato
Author-email: joseph@jdkato.io
License: MIT
Platform: UNKNOWN
Classifier: License :: OSI Approved :: MIT License
Classifier: Programming Language :: Python
Classifier: Programming Language :: Python :: 3
Classifier: Programming Language :: Python :: 3.6
Requires-Python: >=3.6.0
Requires-Dist: requests
Requires-Dist: tabulate
Requires-Dist: xlrd
Requires-Dist: us
